<?xml version="1.0" encoding="UTF-8"?>
<configuration>
    <db-config>
        <jdbc-connection-pool>
            <url>jdbc:mysql://centrallogging.mysql.db.sh.ctripcorp.com:55944/dashboarddb?useUnicode=true</url>
            <driverClassName>com.mysql.jdbc.Driver</driverClassName>
            <username>uapp_dashboard</username>
            <password>Z6OFj8LNdGtOpbeG8f9U</password>
            <initialSize>3</initialSize>
            <maxActive>12</maxActive>
            <maxIdle>3</maxIdle>
            <minIdle>3</minIdle>
            <maxWait>10000</maxWait>
        </jdbc-connection-pool>
    </db-config>
</configuration>
